README.md
setup.cfg
setup.py
gauss_binom_kwo/Binomialdistribution.py
gauss_binom_kwo/Gaussiandistribution.py
gauss_binom_kwo/Generaldistribution.py
gauss_binom_kwo/__init__.py
gauss_binom_kwo.egg-info/PKG-INFO
gauss_binom_kwo.egg-info/SOURCES.txt
gauss_binom_kwo.egg-info/dependency_links.txt
gauss_binom_kwo.egg-info/not-zip-safe
gauss_binom_kwo.egg-info/top_level.txt